README.md
setup.py
Brigada/MySerializer.py
Brigada/__init__.py
Brigada/constants.py
Brigada/json_utils.py
Brigada/pack_utils.py
Brigada/serializer.py
Brigada/unpack_utils.py
Brigada/xml_utils.py
Brigadir.egg-info/PKG-INFO
Brigadir.egg-info/SOURCES.txt
Brigadir.egg-info/dependency_links.txt
Brigadir.egg-info/entry_points.txt
Brigadir.egg-info/top_level.txt
tests/__init__.py
tests/test_attributes.py
tests/unitest.py