Metadata-Version: 2.1
Name: Brigadir
Version: 1.0.1
Summary: JSON and XLM serializer
Author: Maksim Piacherski
Author-email: murzikelite@gmail.com
